CHANGES.txt
README.txt
TODO.txt
bootstrap.py
buildout.cfg
setup.py
src/tha/__init__.py
src/tha.sdistmaker.egg-info/PKG-INFO
src/tha.sdistmaker.egg-info/SOURCES.txt
src/tha.sdistmaker.egg-info/dependency_links.txt
src/tha.sdistmaker.egg-info/entry_points.txt
src/tha.sdistmaker.egg-info/namespace_packages.txt
src/tha.sdistmaker.egg-info/not-zip-safe
src/tha.sdistmaker.egg-info/requires.txt
src/tha.sdistmaker.egg-info/top_level.txt
src/tha/sdistmaker/USAGE.txt
src/tha/sdistmaker/__init__.py
src/tha/sdistmaker/defaults.py
src/tha/sdistmaker/iterator.py
src/tha/sdistmaker/maker.py
src/tha/sdistmaker/tests/__init__.py
src/tha/sdistmaker/tests/sample.txt
src/tha/sdistmaker/tests/test_setup.py