Metadata-Version: 1.0
Name: tha.sdistmaker
Version: 1.0
Summary: UNKNOWN
Home-page: http://www.thehealthagency.com
Author: The Health Agency
Author-email: techniek@thehealthagency.com
License: BSD
Platform: UNKNOWN
